setup.py
moment/__init__.py
moment/base.py
moment/bitevents.py
moment/collections.py
moment/compat.py
moment/conf.py
moment/counters.py
moment/keys.py
moment/lua.py
moment/tests.py
moment/timelines.py
moment/utils.py
moment/contrib/__init__.py
moment/contrib/django.py
redis_moment.egg-info/PKG-INFO
redis_moment.egg-info/SOURCES.txt
redis_moment.egg-info/dependency_links.txt
redis_moment.egg-info/not-zip-safe
redis_moment.egg-info/requires.txt
redis_moment.egg-info/top_level.txt