Metadata-Version: 1.1
Name: redis-moment
Version: 0.0.4
Summary: A Powerful Analytics Python Library for Redis
Home-page: https://github.com/caxap/redis-moment
Author: Max Kamenkov
Author-email: mkamenkov@gmail.com
License: MIT
Platform: UNKNOWN
Classifier: Development Status :: 3 - Alpha
Classifier: Environment :: Web Environment
Classifier: Intended Audience :: Developers
Classifier: License :: OSI Approved :: BSD License
Classifier: Operating System :: POSIX
Classifier: Programming Language :: Python
Classifier: Topic :: System :: Distributed Computing
Classifier: Topic :: Software Development :: Object Brokering
